cwl2argparse/__init__.py
cwl2argparse/argparse.j2
cwl2argparse/cwl_argparse_translation.py
cwl2argparse/cwl_classes.py
cwl2argparse/main.py
cwl2argparse/test_cwl2argparse.py
cwl2argparse-0.1.6.dist-info/DESCRIPTION.rst
cwl2argparse-0.1.6.dist-info/METADATA
cwl2argparse-0.1.6.dist-info/RECORD
cwl2argparse-0.1.6.dist-info/WHEEL
cwl2argparse-0.1.6.dist-info/entry_points.txt
cwl2argparse-0.1.6.dist-info/metadata.json
cwl2argparse-0.1.6.dist-info/top_level.txt
